leaderboard_summarizer/__init__.py
leaderboard_summarizer/main.py
leaderboard_summarizer/prompts.py
leaderboard_summarizer-2025.12.21232414.dist-info/METADATA
leaderboard_summarizer-2025.12.21232414.dist-info/WHEEL
leaderboard_summarizer-2025.12.21232414.dist-info/top_level.txt
leaderboard_summarizer-2025.12.21232414.dist-info/RECORD
