Metadata-Version: 2.4
Name: leaderboard-summarizer
Version: 2025.12.21232414
Summary: Extracts and organizes leaderboard/ranking data from text via smart pattern matching and retries, delivering clean, structured summaries effortlessly.
Author-email: leaderboard-summarizer <hi@eugene.plus>
License: MIT
Project-URL: Homepage, https://github.com/chigwell/leaderboard-summarizer
Requires-Python: >=3.9
Requires-Dist: langchain-llm7>=0.0.0
Requires-Dist: llmatch-messages>=0.0.0
Requires-Dist: langchain-core>=0.3.0
